octoprint_setuptools/__init__.py
OctoPrint_Setuptools-1.0.3.dist-info/LICENSE
OctoPrint_Setuptools-1.0.3.dist-info/METADATA
OctoPrint_Setuptools-1.0.3.dist-info/WHEEL
OctoPrint_Setuptools-1.0.3.dist-info/top_level.txt
OctoPrint_Setuptools-1.0.3.dist-info/RECORD
